serial_sniffer/__init__.py
serial_sniffer/__main__.py
serial_sniffer/main.py
serial_sniffer/sniffer.py
serial_sniffer/tools.py
serial_sniffer/utils.py
serial_sniffer-1.0.1.dist-info/LICENSE
serial_sniffer-1.0.1.dist-info/METADATA
serial_sniffer-1.0.1.dist-info/WHEEL
serial_sniffer-1.0.1.dist-info/entry_points.txt
serial_sniffer-1.0.1.dist-info/top_level.txt
serial_sniffer-1.0.1.dist-info/RECORD
