Metadata-Version: 2.1
Name: serial-sniffer
Version: 1.0.1
Summary: Simple way to sniff dev ports.
Home-page: https://github.com/ido123net/serial-sniffer
Author: Ido Frenkel
Author-email: ido123net@gmail.com
License: MIT
Classifier: License :: OSI Approved :: MIT License
Classifier: Programming Language :: Python :: 3
Classifier: Programming Language :: Python :: 3 :: Only
Classifier: Programming Language :: Python :: Implementation :: CPython
Classifier: Programming Language :: Python :: Implementation :: PyPy
Requires-Python: >=3.7
License-File: LICENSE
Requires-Dist: psutil (>=5.9.4)
Requires-Dist: pyserial (>=3.5)
